powerline_diskspace/__init__.py
powerline_diskspace/diskspace.py
powerline_diskspace/diskspace_test.py
powerline_diskspace-0.1.3.dist-info/METADATA
powerline_diskspace-0.1.3.dist-info/WHEEL
powerline_diskspace-0.1.3.dist-info/licenses/LICENSE
powerline_diskspace-0.1.3.dist-info/RECORD
