Metadata-Version: 2.4
Name: powerline-diskspace
Version: 0.1.3
Summary: A Powerline segment for displaying local disk utilization.
Project-URL: Homepage, https://github.com/AndreiBarsan/powerline-diskspace
Project-URL: Issues, https://github.com/AndreiBarsan/powerline-diskspace/issues
Author: Andrei Bârsan
License-Expression: MIT
License-File: LICENSE
Classifier: Intended Audience :: Developers
Classifier: Intended Audience :: Education
Classifier: Intended Audience :: Science/Research
Classifier: License :: OSI Approved :: MIT License
Classifier: Programming Language :: Python :: 3
Classifier: Topic :: Software Development
Classifier: Topic :: Software Development :: Libraries
Classifier: Topic :: Software Development :: Libraries :: Python Modules
Requires-Python: >=3.8
